pydbsnp/__init__.py
pydbsnp/download.py
pydbsnp/env.py
pydbsnp/index.py
pydbsnp/query.py
pydbsnp-2.0.2.dist-info/LICENSE
pydbsnp-2.0.2.dist-info/METADATA
pydbsnp-2.0.2.dist-info/WHEEL
pydbsnp-2.0.2.dist-info/entry_points.txt
pydbsnp-2.0.2.dist-info/top_level.txt
pydbsnp-2.0.2.dist-info/RECORD
