Metadata-Version: 2.1
Name: pydbsnp
Version: 2.0.2
Summary: Interface with dbSNP VCF data
Home-page: https://gitlab.com/aaylward/pydbsnp
Author: Anthony Aylward
Author-email: aaylward@salk.edu
License: UNKNOWN
Platform: UNKNOWN
Classifier: Programming Language :: Python :: 3
Classifier: License :: OSI Approved :: MIT License
Classifier: Operating System :: OS Independent
License-File: LICENSE
Requires-Dist: pysam
